{
  "fighter_id": "7832f2f62f04178f",
  "ratings": {
    "knockout_power": {
      "dimension": "knockout_power",
      "rating": 1482.511789891318,
      "games_played": 8,
      "last_updated": "2023-07-15"
    },
    "striking_volume": {
      "dimension": "striking_volume",
      "rating": 1502.4840842769738,
      "games_played": 8,
      "last_updated": "2023-07-15"
    },
    "striking_defense": {
      "dimension": "striking_defense",
      "rating": 1484.3041341121254,
      "games_played": 8,
      "last_updated": "2023-07-15"
    },
    "wrestling_offense": {
      "dimension": "wrestling_offense",
      "rating": 1495.4493546495528,
      "games_played": 8,
      "last_updated": "2023-07-15"
    },
    "wrestling_defense": {
      "dimension": "wrestling_defense",
      "rating": 1520.5424758879662,
      "games_played": 8,
      "last_updated": "2023-07-15"
    },
    "submission_offense": {
      "dimension": "submission_offense",
      "rating": 1483.695744617144,
      "games_played": 8,
      "last_updated": "2023-07-15"
    },
    "submission_defense": {
      "dimension": "submission_defense",
      "rating": 1489.249999275872,
      "games_played": 8,
      "last_updated": "2023-07-15"
    },
    "cardio": {
      "dimension": "cardio",
      "rating": 1496.7884802231713,
      "games_played": 8,
      "last_updated": "2023-07-15"
    },
    "pressure": {
      "dimension": "pressure",
      "rating": 1494.474456187989,
      "games_played": 8,
      "last_updated": "2023-07-15"
    },
    "adaptability": {
      "dimension": "adaptability",
      "rating": 1488.9753072812919,
      "games_played": 8,
      "last_updated": "2023-07-15"
    }
  },
  "ko_losses": 0,
  "last_fight_date": "2023-07-15",
  "total_fights": 8
}