{
  "fight_id": "19fc916df1f0e6ff",
  "event_id": "d29b5c4f22c6357d",
  "fighter1_id": "f046d724d2a84ac5",
  "fighter2_id": "75e5fec9f72910ef",
  "winner_id": "f046d724d2a84ac5",
  "weight_class": "Lightweight",
  "is_title_fight": false,
  "is_main_event": false,
  "method": "Decision",
  "method_detail": "Unanimous",
  "round_finished": 3,
  "time_finished": "5:00",
  "scheduled_rounds": 3,
  "referee": "Dan Miragliotta",
  "fighter1_stats": {
    "fighter_id": "f046d724d2a84ac5",
    "knockdowns": 0,
    "sig_strikes_landed": 77,
    "sig_strikes_attempted": 191,
    "total_strikes_landed": 77,
    "total_strikes_attempted": 191,
    "takedowns_landed": 0,
    "takedowns_attempted": 0,
    "sub_attempts": 0,
    "reversals": 0,
    "control_time_seconds": 0,
    "round_stats": []
  },
  "fighter2_stats": {
    "fighter_id": "75e5fec9f72910ef",
    "knockdowns": 0,
    "sig_strikes_landed": 28,
    "sig_strikes_attempted": 178,
    "total_strikes_landed": 29,
    "total_strikes_attempted": 179,
    "takedowns_landed": 0,
    "takedowns_attempted": 3,
    "sub_attempts": 0,
    "reversals": 0,
    "control_time_seconds": 0,
    "round_stats": []
  }
}