{
  "fight_id": "23e5acd1549b538a",
  "event_id": "9e30f69cc0869301",
  "fighter1_id": "33a331684283900f",
  "fighter2_id": "9e8f6c728eb01124",
  "winner_id": "33a331684283900f",
  "weight_class": "Lightweight",
  "is_title_fight": false,
  "is_main_event": false,
  "method": "KO/TKO",
  "method_detail": null,
  "round_finished": 3,
  "time_finished": "3:59",
  "scheduled_rounds": 3,
  "referee": "Herb Dean",
  "fighter1_stats": {
    "fighter_id": "33a331684283900f",
    "knockdowns": 1,
    "sig_strikes_landed": 155,
    "sig_strikes_attempted": 356,
    "total_strikes_landed": 162,
    "total_strikes_attempted": 366,
    "takedowns_landed": 1,
    "takedowns_attempted": 2,
    "sub_attempts": 0,
    "reversals": 0,
    "control_time_seconds": 20,
    "round_stats": []
  },
  "fighter2_stats": {
    "fighter_id": "9e8f6c728eb01124",
    "knockdowns": 0,
    "sig_strikes_landed": 122,
    "sig_strikes_attempted": 237,
    "total_strikes_landed": 124,
    "total_strikes_attempted": 240,
    "takedowns_landed": 0,
    "takedowns_attempted": 1,
    "sub_attempts": 0,
    "reversals": 0,
    "control_time_seconds": 6,
    "round_stats": []
  }
}