{
  "fight_id": "23e548f618dd0e5f",
  "event_id": "af1e5c64b8663aa0",
  "fighter1_id": "d2cd7a69cc55e7ed",
  "fighter2_id": "af65aa688d13eedf",
  "winner_id": "af65aa688d13eedf",
  "weight_class": "Lightweight",
  "is_title_fight": false,
  "is_main_event": false,
  "method": "Submission",
  "method_detail": null,
  "round_finished": 1,
  "time_finished": "3:51",
  "scheduled_rounds": 3,
  "referee": "Herb Dean",
  "fighter1_stats": {
    "fighter_id": "d2cd7a69cc55e7ed",
    "knockdowns": 0,
    "sig_strikes_landed": 9,
    "sig_strikes_attempted": 14,
    "total_strikes_landed": 9,
    "total_strikes_attempted": 14,
    "takedowns_landed": 0,
    "takedowns_attempted": 0,
    "sub_attempts": 0,
    "reversals": 0,
    "control_time_seconds": 0,
    "round_stats": []
  },
  "fighter2_stats": {
    "fighter_id": "af65aa688d13eedf",
    "knockdowns": 0,
    "sig_strikes_landed": 13,
    "sig_strikes_attempted": 20,
    "total_strikes_landed": 36,
    "total_strikes_attempted": 43,
    "takedowns_landed": 0,
    "takedowns_attempted": 2,
    "sub_attempts": 1,
    "reversals": 0,
    "control_time_seconds": 157,
    "round_stats": []
  }
}