{
  "fight_id": "7024385b5107bd4b",
  "event_id": "13a0fb8fbdafb54f",
  "fighter1_id": "b07aed698fba8624",
  "fighter2_id": "d317a5e2b3f88c5f",
  "winner_id": "b07aed698fba8624",
  "weight_class": "Middleweight",
  "is_title_fight": false,
  "is_main_event": false,
  "method": "KO/TKO",
  "method_detail": null,
  "round_finished": 1,
  "time_finished": "2:07",
  "scheduled_rounds": 3,
  "referee": "Lukasz Bosacki",
  "fighter1_stats": {
    "fighter_id": "b07aed698fba8624",
    "knockdowns": 1,
    "sig_strikes_landed": 26,
    "sig_strikes_attempted": 36,
    "total_strikes_landed": 26,
    "total_strikes_attempted": 36,
    "takedowns_landed": 0,
    "takedowns_attempted": 0,
    "sub_attempts": 0,
    "reversals": 0,
    "control_time_seconds": 0,
    "round_stats": []
  },
  "fighter2_stats": {
    "fighter_id": "d317a5e2b3f88c5f",
    "knockdowns": 0,
    "sig_strikes_landed": 12,
    "sig_strikes_attempted": 16,
    "total_strikes_landed": 12,
    "total_strikes_attempted": 16,
    "takedowns_landed": 0,
    "takedowns_attempted": 0,
    "sub_attempts": 0,
    "reversals": 0,
    "control_time_seconds": 0,
    "round_stats": []
  }
}