{
  "fight_id": "87c8e086c29ae543",
  "event_id": "9ddfb3369a3b0394",
  "fighter1_id": "2558ae2e5671e318",
  "fighter2_id": "4aa58269d0664b5b",
  "winner_id": "2558ae2e5671e318",
  "weight_class": "Welterweight",
  "is_title_fight": false,
  "is_main_event": false,
  "method": "Decision",
  "method_detail": "Unanimous",
  "round_finished": 3,
  "time_finished": "5:00",
  "scheduled_rounds": 3,
  "referee": "Herb Dean",
  "fighter1_stats": {
    "fighter_id": "2558ae2e5671e318",
    "knockdowns": 0,
    "sig_strikes_landed": 91,
    "sig_strikes_attempted": 260,
    "total_strikes_landed": 114,
    "total_strikes_attempted": 286,
    "takedowns_landed": 0,
    "takedowns_attempted": 0,
    "sub_attempts": 0,
    "reversals": 0,
    "control_time_seconds": 113,
    "round_stats": []
  },
  "fighter2_stats": {
    "fighter_id": "4aa58269d0664b5b",
    "knockdowns": 0,
    "sig_strikes_landed": 64,
    "sig_strikes_attempted": 141,
    "total_strikes_landed": 68,
    "total_strikes_attempted": 146,
    "takedowns_landed": 0,
    "takedowns_attempted": 0,
    "sub_attempts": 0,
    "reversals": 0,
    "control_time_seconds": 2,
    "round_stats": []
  }
}