{
  "fight_id": "afd53c8033f6ee82",
  "event_id": "563d051c9e769b24",
  "fighter1_id": "4a57ebb14315b251",
  "fighter2_id": "1a98c9dbb7fc3959",
  "winner_id": "4a57ebb14315b251",
  "weight_class": "Women's Strawweight",
  "is_title_fight": false,
  "is_main_event": false,
  "method": "Decision",
  "method_detail": "Unanimous",
  "round_finished": 3,
  "time_finished": "5:00",
  "scheduled_rounds": 3,
  "referee": "Herb Dean",
  "fighter1_stats": {
    "fighter_id": "4a57ebb14315b251",
    "knockdowns": 0,
    "sig_strikes_landed": 86,
    "sig_strikes_attempted": 243,
    "total_strikes_landed": 116,
    "total_strikes_attempted": 284,
    "takedowns_landed": 1,
    "takedowns_attempted": 6,
    "sub_attempts": 1,
    "reversals": 0,
    "control_time_seconds": 119,
    "round_stats": []
  },
  "fighter2_stats": {
    "fighter_id": "1a98c9dbb7fc3959",
    "knockdowns": 0,
    "sig_strikes_landed": 79,
    "sig_strikes_attempted": 235,
    "total_strikes_landed": 96,
    "total_strikes_attempted": 252,
    "takedowns_landed": 1,
    "takedowns_attempted": 1,
    "sub_attempts": 0,
    "reversals": 0,
    "control_time_seconds": 110,
    "round_stats": []
  }
}