{
  "fight_id": "b65b37c0e00074d9",
  "event_id": "89a407032911e27e",
  "fighter1_id": "a68575214ecad140",
  "fighter2_id": "082eba4cd80f736f",
  "winner_id": "a68575214ecad140",
  "weight_class": "Featherweight",
  "is_title_fight": false,
  "is_main_event": false,
  "method": "Decision",
  "method_detail": "Unanimous",
  "round_finished": 3,
  "time_finished": "5:00",
  "scheduled_rounds": 3,
  "referee": "Thomas Fan",
  "fighter1_stats": {
    "fighter_id": "a68575214ecad140",
    "knockdowns": 1,
    "sig_strikes_landed": 56,
    "sig_strikes_attempted": 115,
    "total_strikes_landed": 108,
    "total_strikes_attempted": 179,
    "takedowns_landed": 1,
    "takedowns_attempted": 1,
    "sub_attempts": 0,
    "reversals": 0,
    "control_time_seconds": 321,
    "round_stats": []
  },
  "fighter2_stats": {
    "fighter_id": "082eba4cd80f736f",
    "knockdowns": 1,
    "sig_strikes_landed": 30,
    "sig_strikes_attempted": 76,
    "total_strikes_landed": 40,
    "total_strikes_attempted": 88,
    "takedowns_landed": 0,
    "takedowns_attempted": 4,
    "sub_attempts": 0,
    "reversals": 0,
    "control_time_seconds": 94,
    "round_stats": []
  }
}