{
  "fight_id": "cc2809e10315a6b5",
  "event_id": "9e30f69cc0869301",
  "fighter1_id": "056c493bbd76a918",
  "fighter2_id": "de75d1c45a39e221",
  "winner_id": "056c493bbd76a918",
  "weight_class": "Flyweight",
  "is_title_fight": false,
  "is_main_event": false,
  "method": "Decision",
  "method_detail": "Unanimous",
  "round_finished": 3,
  "time_finished": "5:00",
  "scheduled_rounds": 3,
  "referee": "Keith Peterson",
  "fighter1_stats": {
    "fighter_id": "056c493bbd76a918",
    "knockdowns": 0,
    "sig_strikes_landed": 36,
    "sig_strikes_attempted": 83,
    "total_strikes_landed": 85,
    "total_strikes_attempted": 148,
    "takedowns_landed": 3,
    "takedowns_attempted": 5,
    "sub_attempts": 0,
    "reversals": 0,
    "control_time_seconds": 574,
    "round_stats": []
  },
  "fighter2_stats": {
    "fighter_id": "de75d1c45a39e221",
    "knockdowns": 0,
    "sig_strikes_landed": 25,
    "sig_strikes_attempted": 98,
    "total_strikes_landed": 38,
    "total_strikes_attempted": 112,
    "takedowns_landed": 0,
    "takedowns_attempted": 1,
    "sub_attempts": 0,
    "reversals": 0,
    "control_time_seconds": 0,
    "round_stats": []
  }
}