{
  "fight_id": "d373de3e072f7e57",
  "event_id": "d56bb6dff2ae77eb",
  "fighter1_id": "d4c9dcd330403612",
  "fighter2_id": "cc98d857b148e33a",
  "winner_id": "d4c9dcd330403612",
  "weight_class": "Middleweight",
  "is_title_fight": false,
  "is_main_event": false,
  "method": "Decision",
  "method_detail": "Unanimous",
  "round_finished": 3,
  "time_finished": "5:00",
  "scheduled_rounds": 3,
  "referee": "Chip Snider",
  "fighter1_stats": {
    "fighter_id": "d4c9dcd330403612",
    "knockdowns": 0,
    "sig_strikes_landed": 57,
    "sig_strikes_attempted": 101,
    "total_strikes_landed": 66,
    "total_strikes_attempted": 111,
    "takedowns_landed": 2,
    "takedowns_attempted": 5,
    "sub_attempts": 0,
    "reversals": 0,
    "control_time_seconds": 236,
    "round_stats": []
  },
  "fighter2_stats": {
    "fighter_id": "cc98d857b148e33a",
    "knockdowns": 0,
    "sig_strikes_landed": 64,
    "sig_strikes_attempted": 108,
    "total_strikes_landed": 121,
    "total_strikes_attempted": 169,
    "takedowns_landed": 0,
    "takedowns_attempted": 0,
    "sub_attempts": 0,
    "reversals": 0,
    "control_time_seconds": 215,
    "round_stats": []
  }
}