{
  "fight_id": "ebb685a81f65ce1b",
  "event_id": "84283233ec42be5f",
  "fighter1_id": "2ac4628c08ec5125",
  "fighter2_id": "093e1f5bb73850be",
  "winner_id": "2ac4628c08ec5125",
  "weight_class": "Middleweight",
  "is_title_fight": false,
  "is_main_event": false,
  "method": "Submission",
  "method_detail": null,
  "round_finished": 2,
  "time_finished": "1:07",
  "scheduled_rounds": 3,
  "referee": "Eduardo Herdy",
  "fighter1_stats": {
    "fighter_id": "2ac4628c08ec5125",
    "knockdowns": 0,
    "sig_strikes_landed": 16,
    "sig_strikes_attempted": 32,
    "total_strikes_landed": 19,
    "total_strikes_attempted": 35,
    "takedowns_landed": 1,
    "takedowns_attempted": 7,
    "sub_attempts": 1,
    "reversals": 0,
    "control_time_seconds": 160,
    "round_stats": []
  },
  "fighter2_stats": {
    "fighter_id": "093e1f5bb73850be",
    "knockdowns": 0,
    "sig_strikes_landed": 17,
    "sig_strikes_attempted": 35,
    "total_strikes_landed": 21,
    "total_strikes_attempted": 39,
    "takedowns_landed": 0,
    "takedowns_attempted": 0,
    "sub_attempts": 0,
    "reversals": 0,
    "control_time_seconds": 37,
    "round_stats": []
  }
}